pyba/README.md
pyba/__init__.py
pyba/cli/__init__.py
pyba/cli/cli_core/__init__.py
pyba/cli/cli_core/arg_parser.py
pyba/cli/cli_core/cli_main.py
pyba/cli/cli_entry.py
pyba/config.yaml
pyba/core/__init__.py
pyba/core/agent/__init__.py
pyba/core/agent/base_agent.py
pyba/core/agent/extraction_agent.py
pyba/core/agent/llm_factory.py
pyba/core/agent/planner_agent.py
pyba/core/agent/playwright_agent.py
pyba/core/helpers/__init__.py
pyba/core/helpers/jitters.py
pyba/core/lib/__init__.py
pyba/core/lib/action.py
pyba/core/lib/code_generation.py
pyba/core/lib/handle_dependencies.py
pyba/core/lib/mode/BFS.py
pyba/core/lib/mode/DFS.py
pyba/core/lib/mode/__init__.py
pyba/core/lib/mode/base.py
pyba/core/main.py
pyba/core/provider.py
pyba/core/scripts/README.md
pyba/core/scripts/__init__.py
pyba/core/scripts/extractions/__init__.py
pyba/core/scripts/extractions/extraction_configs.yaml
pyba/core/scripts/extractions/general.py
pyba/core/scripts/extractions/youtube_.py
pyba/core/scripts/js/extractions.js
pyba/core/scripts/login/README.md
pyba/core/scripts/login/__init__.py
pyba/core/scripts/login/base.py
pyba/core/scripts/login/facebook.py
pyba/core/scripts/login/gmail.py
pyba/core/scripts/login/instagram.py
pyba/core/tracing.py
pyba/database/README.md
pyba/database/__init__.py
pyba/database/database.py
pyba/database/db_funcs.py
pyba/database/models.py
pyba/database/mysql.py
pyba/database/postgres.py
pyba/database/sqlite.py
pyba/database/vectordb/__init__.py
pyba/database/vectordb/pinecone_setup.py
pyba/idea.md
pyba/logger.py
pyba/utils/__init__.py
pyba/utils/common.py
pyba/utils/exceptions.py
pyba/utils/load_yaml.py
pyba/utils/prompts/__init__.py
pyba/utils/prompts/extraction_prompts.py
pyba/utils/prompts/general_prompt.py
pyba/utils/prompts/output_general_prompt.py
pyba/utils/prompts/output_system_prompt.py
pyba/utils/prompts/planner_agent_prompt.py
pyba/utils/prompts/system_prompt.py
pyba/utils/structure.py
pyba/version.py
py_browser_automation-0.3.1.dist-info/METADATA
py_browser_automation-0.3.1.dist-info/WHEEL
py_browser_automation-0.3.1.dist-info/entry_points.txt
py_browser_automation-0.3.1.dist-info/licenses/LICENSE
py_browser_automation-0.3.1.dist-info/RECORD
