Metadata-Version: 2.4
Name: py-browser-automation
Version: 0.3.1
Summary: Automate online browsing using python and AI
License: MIT
License-File: LICENSE
Keywords: browser-automations,AI
Author: pUrGe12
Author-email: achintya.jai@owasp.org
Requires-Python: >=3.10,<4.0
Classifier: License :: OSI Approved :: MIT License
Classifier: Operating System :: OS Independent
Classifier: Programming Language :: Python :: 3
Classifier: Programming Language :: Python :: 3.10
Classifier: Programming Language :: Python :: 3.11
Classifier: Programming Language :: Python :: 3.12
Classifier: Programming Language :: Python :: 3.13
Classifier: Programming Language :: Python :: 3.14
Requires-Dist: bs4 (>=0.0.2,<0.0.3)
Requires-Dist: colorama (>=0.4.6,<0.5.0)
Requires-Dist: google-genai (>=1.45.0,<2.0.0)
Requires-Dist: openai (>=2.6.0,<3.0.0)
Requires-Dist: oxymouse (>=1.1.0,<2.0.0)
Requires-Dist: playwright (>=1.55.0,<2.0.0)
Requires-Dist: playwright-stealth (>=2.0.0,<3.0.0)
Requires-Dist: pydantic (>=2.12.0,<3.0.0)
Requires-Dist: python-dotenv (>=1.1.1,<2.0.0)
Requires-Dist: pyyaml (>=6.0.3,<7.0.0)
Requires-Dist: requests (>=2.32.5,<3.0.0)
Requires-Dist: sqlalchemy (>=2.0.44,<3.0.0)
Project-URL: Documentation, https://pyba.readthedocs.io/
